[
  {
    "source": "MLB.com",
    "title": "Lindor exits game with left calf tightness",
    "url": "https://www.mlb.com/mets/news/francisco-lindor-exits-vs-twins-with-calf-injury"
  },
  {
    "source": "MLB.com",
    "title": "Mets activate Soto from IL as they try to end 12-game skid",
    "url": "https://www.mlb.com/mets/news/juan-soto-mets-injured-list-return-plans"
  },
  {
    "source": "MLB.com",
    "title": "Stream Mets games through the MLB App",
    "url": "https://www.mlb.com/mets/news/sny-mets-mlb-2026-stream"
  },
  {
    "source": "MLB.com",
    "title": "Check out the 2,200+ MiLB games that you can get tickets to for just 10 bucks",
    "url": "https://www.mlb.com/mets/news/see-any-minor-league-team-for-10"
  },
  {
    "source": "MLB.com",
    "title": "These prospects are bringing the heat for their respective organizations",
    "url": "https://www.mlb.com/mets/news/each-team-s-prospect-with-the-best-fastball-2026"
  }
]