[
  {
    "source": "MLB.com",
    "title": "Ron Hunt, known for HBP records and unique spirit, dies at 85",
    "url": "https://www.mlb.com/mets/news/ron-hunt-dies-at-85"
  },
  {
    "source": "MLB.com",
    "title": "Beltrán nearing induction as 3rd Met, 6th Puerto Rican in Hall of Fame",
    "url": "https://www.mlb.com/mets/news/carlos-beltran-hall-of-fame-induction"
  },
  {
    "source": "MLB.com",
    "title": "Price drop! Stream Mets games through the MLB App",
    "url": "https://www.mlb.com/mets/news/sny-mets-mlb-2026-stream"
  },
  {
    "source": "MLB.com",
    "title": "Mets reportedly Deadline sellers with very few names off the table",
    "url": "https://www.mlb.com/mets/news/mets-ready-to-sell-at-2026-trade-deadline-sources"
  },
  {
    "source": "MLB.com",
    "title": "Each team's biggest trade chip as Deadline nears",
    "url": "https://www.mlb.com/mets/news/every-mlb-team-biggest-trade-deadline-chip-2026"
  }
]